{".class": "MypyFile", "_fullname": "simple_playgrounds.elements.collection.zone", "is_partial_stub_package": false, "is_stub": false, "names": {".class": "SymbolTable", "ABC": {".class": "SymbolTableNode", "cross_ref": "abc.ABC", "kind": "Gdef"}, "DeathZone": {".class": "SymbolTableNode", "kind": "Gdef", "node": {".class": "TypeInfo", "_promote": null, "abstract_attributes": [], "bases": ["simple_playgrounds.elements.collection.zone.TerminationZone"], "declared_metaclass": null, "defn": {".class": "ClassDef", "fullname": "simple_playgrounds.elements.collection.zone.DeathZone", "name": "DeathZone", "type_vars": []}, "flags": [], "fullname": "simple_playgrounds.elements.collection.zone.DeathZone", "metaclass_type": "abc.ABCMeta", "metadata": {}, "module_name": "simple_playgrounds.elements.collection.zone", "mro": ["simple_playgrounds.elements.collection.zone.DeathZone", "simple_playgrounds.elements.collection.zone.TerminationZone", "simple_playgrounds.elements.element.ZoneElement", "simple_playgrounds.elements.element.InteractiveElement", "simple_playgrounds.elements.element.SceneElement", "simple_playgrounds.common.entity.Entity", "abc.ABC", "builtins.object"], "names": {".class": "SymbolTable", "__init__": {".class": "SymbolTableNode", "kind": "Mdef", "node": {".class": "FuncDef", "arg_kinds": [0, 0, 4], "arg_names": ["self", "reward", "kwargs"], "flags": [], "fullname": "simple_playgrounds.elements.collection.zone.DeathZone.__init__", "name": "__init__", "type": {".class": "CallableType", "arg_kinds": [0, 0, 4], "arg_names": ["self", "reward", "kwargs"], "arg_types": ["simple_playgrounds.elements.collection.zone.DeathZone", "builtins.float", {".class": "AnyType", "missing_import_name": null, "source_any": null, "type_of_any": 1}], "bound_args": [], "def_extras": {"first_arg": "self"}, "fallback": "builtins.function", "implicit": false, "is_ellipsis_args": false, "name": "__init__ of DeathZone", "ret_type": {".class": "NoneType"}, "variables": []}}}}, "tuple_type": null, "type_vars": [], "typeddict_type": null}}, "ElementTypes": {".class": "SymbolTableNode", "cross_ref": "simple_playgrounds.definitions.ElementTypes", "kind": "Gdef"}, "GoalZone": {".class": "SymbolTableNode", "kind": "Gdef", "node": {".class": "TypeInfo", "_promote": null, "abstract_attributes": [], "bases": ["simple_playgrounds.elements.collection.zone.TerminationZone"], "declared_metaclass": null, "defn": {".class": "ClassDef", "fullname": "simple_playgrounds.elements.collection.zone.GoalZone", "name": "GoalZone", "type_vars": []}, "flags": [], "fullname": "simple_playgrounds.elements.collection.zone.GoalZone", "metaclass_type": "abc.ABCMeta", "metadata": {}, "module_name": "simple_playgrounds.elements.collection.zone", "mro": ["simple_playgrounds.elements.collection.zone.GoalZone", "simple_playgrounds.elements.collection.zone.TerminationZone", "simple_playgrounds.elements.element.ZoneElement", "simple_playgrounds.elements.element.InteractiveElement", "simple_playgrounds.elements.element.SceneElement", "simple_playgrounds.common.entity.Entity", "abc.ABC", "builtins.object"], "names": {".class": "SymbolTable", "__init__": {".class": "SymbolTableNode", "kind": "Mdef", "node": {".class": "FuncDef", "arg_kinds": [0, 0, 4], "arg_names": ["self", "reward", "kwargs"], "flags": [], "fullname": "simple_playgrounds.elements.collection.zone.GoalZone.__init__", "name": "__init__", "type": {".class": "CallableType", "arg_kinds": [0, 0, 4], "arg_names": ["self", "reward", "kwargs"], "arg_types": ["simple_playgrounds.elements.collection.zone.GoalZone", "builtins.float", {".class": "AnyType", "missing_import_name": null, "source_any": null, "type_of_any": 1}], "bound_args": [], "def_extras": {"first_arg": "self"}, "fallback": "builtins.function", "implicit": false, "is_ellipsis_args": false, "name": "__init__ of GoalZone", "ret_type": {".class": "NoneType"}, "variables": []}}}}, "tuple_type": null, "type_vars": [], "typeddict_type": null}}, "HealingZone": {".class": "SymbolTableNode", "kind": "Gdef", "node": {".class": "TypeInfo", "_promote": null, "abstract_attributes": [], "bases": ["simple_playgrounds.elements.collection.zone.RewardZone"], "declared_metaclass": null, "defn": {".class": "ClassDef", "fullname": "simple_playgrounds.elements.collection.zone.HealingZone", "name": "HealingZone", "type_vars": []}, "flags": [], "fullname": "simple_playgrounds.elements.collection.zone.HealingZone", "metaclass_type": "abc.ABCMeta", "metadata": {}, "module_name": "simple_playgrounds.elements.collection.zone", "mro": ["simple_playgrounds.elements.collection.zone.HealingZone", "simple_playgrounds.elements.collection.zone.RewardZone", "simple_playgrounds.elements.element.ZoneElement", "simple_playgrounds.elements.element.InteractiveElement", "simple_playgrounds.elements.element.SceneElement", "simple_playgrounds.common.entity.Entity", "abc.ABC", "builtins.object"], "names": {".class": "SymbolTable", "__init__": {".class": "SymbolTableNode", "kind": "Mdef", "node": {".class": "FuncDef", "arg_kinds": [0, 0, 0, 4], "arg_names": ["self", "reward", "limit", "entity_params"], "flags": [], "fullname": "simple_playgrounds.elements.collection.zone.HealingZone.__init__", "name": "__init__", "type": {".class": "CallableType", "arg_kinds": [0, 0, 0, 4], "arg_names": ["self", "reward", "limit", "entity_params"], "arg_types": ["simple_playgrounds.elements.collection.zone.HealingZone", "builtins.float", {".class": "UnionType", "items": ["builtins.float", {".class": "NoneType"}]}, {".class": "AnyType", "missing_import_name": null, "source_any": null, "type_of_any": 1}], "bound_args": [], "def_extras": {"first_arg": "self"}, "fallback": "builtins.function", "implicit": false, "is_ellipsis_args": false, "name": "__init__ of HealingZone", "ret_type": {".class": "NoneType"}, "variables": []}}}}, "tuple_type": null, "type_vars": [], "typeddict_type": null}}, "Optional": {".class": "SymbolTableNode", "cross_ref": "typing.Optional", "kind": "Gdef"}, "RewardZone": {".class": "SymbolTableNode", "kind": "Gdef", "node": {".class": "TypeInfo", "_promote": null, "abstract_attributes": [], "bases": ["simple_playgrounds.elements.element.ZoneElement", "abc.ABC"], "declared_metaclass": null, "defn": {".class": "ClassDef", "fullname": "simple_playgrounds.elements.collection.zone.RewardZone", "name": "RewardZone", "type_vars": []}, "flags": [], "fullname": "simple_playgrounds.elements.collection.zone.RewardZone", "metaclass_type": "abc.ABCMeta", "metadata": {}, "module_name": "simple_playgrounds.elements.collection.zone", "mro": ["simple_playgrounds.elements.collection.zone.RewardZone", "simple_playgrounds.elements.element.ZoneElement", "simple_playgrounds.elements.element.InteractiveElement", "simple_playgrounds.elements.element.SceneElement", "simple_playgrounds.common.entity.Entity", "abc.ABC", "builtins.object"], "names": {".class": "SymbolTable", "__init__": {".class": "SymbolTableNode", "kind": "Mdef", "node": {".class": "FuncDef", "arg_kinds": [0, 0, 0, 0, 4], "arg_names": ["self", "config_key", "reward", "limit", "entity_params"], "flags": [], "fullname": "simple_playgrounds.elements.collection.zone.RewardZone.__init__", "name": "__init__", "type": {".class": "CallableType", "arg_kinds": [0, 0, 0, 0, 4], "arg_names": ["self", "config_key", "reward", "limit", "entity_params"], "arg_types": ["simple_playgrounds.elements.collection.zone.RewardZone", {".class": "AnyType", "missing_import_name": null, "source_any": null, "type_of_any": 1}, "builtins.float", {".class": "UnionType", "items": ["builtins.float", {".class": "NoneType"}]}, {".class": "AnyType", "missing_import_name": null, "source_any": null, "type_of_any": 1}], "bound_args": [], "def_extras": {"first_arg": "self"}, "fallback": "builtins.function", "implicit": false, "is_ellipsis_args": false, "name": "__init__ of RewardZone", "ret_type": {".class": "NoneType"}, "variables": []}}}, "_limit": {".class": "SymbolTableNode", "implicit": true, "kind": "Mdef", "node": {".class": "Var", "flags": [], "fullname": "simple_playgrounds.elements.collection.zone.RewardZone._limit", "name": "_limit", "type": {".class": "UnionType", "items": ["builtins.float", {".class": "NoneType"}]}}}, "_total_reward_provided": {".class": "SymbolTableNode", "implicit": true, "kind": "Mdef", "node": {".class": "Var", "flags": [], "fullname": "simple_playgrounds.elements.collection.zone.RewardZone._total_reward_provided", "name": "_total_reward_provided", "type": "builtins.int"}}, "activate": {".class": "SymbolTableNode", "kind": "Mdef", "node": {".class": "FuncDef", "arg_kinds": [0, 2], "arg_names": ["self", "args"], "flags": [], "fullname": "simple_playgrounds.elements.collection.zone.RewardZone.activate", "name": "activate", "type": null}}, "reset": {".class": "SymbolTableNode", "kind": "Mdef", "node": {".class": "FuncDef", "arg_kinds": [0], "arg_names": ["self"], "flags": [], "fullname": "simple_playgrounds.elements.collection.zone.RewardZone.reset", "name": "reset", "type": null}}, "reward": {".class": "SymbolTableNode", "kind": "Mdef", "node": {".class": "OverloadedFuncDef", "flags": ["is_property"], "fullname": "simple_playgrounds.elements.collection.zone.RewardZone.reward", "impl": null, "items": [{".class": "Decorator", "func": {".class": "FuncDef", "arg_kinds": [0], "arg_names": ["self"], "flags": ["is_property", "is_overload", "is_decorated"], "fullname": "simple_playgrounds.elements.collection.zone.RewardZone.reward", "name": "reward", "type": null}, "is_overload": true, "var": {".class": "Var", "flags": ["is_initialized_in_class", "is_property", "is_settable_property", "is_ready"], "fullname": null, "name": "reward", "type": {".class": "CallableType", "arg_kinds": [0], "arg_names": ["self"], "arg_types": ["simple_playgrounds.elements.collection.zone.RewardZone"], "bound_args": [], "def_extras": {}, "fallback": "builtins.function", "implicit": true, "is_ellipsis_args": false, "name": "reward of RewardZone", "ret_type": {".class": "AnyType", "missing_import_name": null, "source_any": null, "type_of_any": 1}, "variables": []}}}, {".class": "Decorator", "func": {".class": "FuncDef", "arg_kinds": [0, 0], "arg_names": ["self", "rew"], "flags": ["is_decorated"], "fullname": "simple_playgrounds.elements.collection.zone.RewardZone.reward", "name": "reward", "type": {".class": "CallableType", "arg_kinds": [0, 0], "arg_names": ["self", "rew"], "arg_types": ["simple_playgrounds.elements.collection.zone.RewardZone", "builtins.float"], "bound_args": [], "def_extras": {"first_arg": "self"}, "fallback": "builtins.function", "implicit": false, "is_ellipsis_args": false, "name": "reward of RewardZone", "ret_type": {".class": "AnyType", "missing_import_name": null, "source_any": null, "type_of_any": 1}, "variables": []}}, "is_overload": false, "var": {".class": "Var", "flags": [], "fullname": null, "name": "reward", "type": null}}], "type": {".class": "Overloaded", "items": [{".class": "CallableType", "arg_kinds": [0], "arg_names": ["self"], "arg_types": ["simple_playgrounds.elements.collection.zone.RewardZone"], "bound_args": [], "def_extras": {}, "fallback": "builtins.function", "implicit": true, "is_ellipsis_args": false, "name": "reward", "ret_type": {".class": "AnyType", "missing_import_name": null, "source_any": null, "type_of_any": 1}, "variables": []}]}}}, "terminate_upon_activation": {".class": "SymbolTableNode", "kind": "Mdef", "node": {".class": "Decorator", "func": {".class": "FuncDef", "arg_kinds": [0], "arg_names": ["self"], "flags": ["is_property", "is_decorated"], "fullname": "simple_playgrounds.elements.collection.zone.RewardZone.terminate_upon_activation", "name": "terminate_upon_activation", "type": null}, "is_overload": false, "var": {".class": "Var", "flags": ["is_initialized_in_class", "is_property", "is_ready"], "fullname": null, "name": "terminate_upon_activation", "type": {".class": "CallableType", "arg_kinds": [0], "arg_names": ["self"], "arg_types": ["simple_playgrounds.elements.collection.zone.RewardZone"], "bound_args": [], "def_extras": {}, "fallback": "builtins.function", "implicit": true, "is_ellipsis_args": false, "name": "terminate_upon_activation of RewardZone", "ret_type": {".class": "AnyType", "missing_import_name": null, "source_any": null, "type_of_any": 1}, "variables": []}}}}}, "tuple_type": null, "type_vars": [], "typeddict_type": null}}, "TerminationZone": {".class": "SymbolTableNode", "kind": "Gdef", "node": {".class": "TypeInfo", "_promote": null, "abstract_attributes": [], "bases": ["simple_playgrounds.elements.element.ZoneElement", "abc.ABC"], "declared_metaclass": null, "defn": {".class": "ClassDef", "fullname": "simple_playgrounds.elements.collection.zone.TerminationZone", "name": "TerminationZone", "type_vars": []}, "flags": [], "fullname": "simple_playgrounds.elements.collection.zone.TerminationZone", "metaclass_type": "abc.ABCMeta", "metadata": {}, "module_name": "simple_playgrounds.elements.collection.zone", "mro": ["simple_playgrounds.elements.collection.zone.TerminationZone", "simple_playgrounds.elements.element.ZoneElement", "simple_playgrounds.elements.element.InteractiveElement", "simple_playgrounds.elements.element.SceneElement", "simple_playgrounds.common.entity.Entity", "abc.ABC", "builtins.object"], "names": {".class": "SymbolTable", "__init__": {".class": "SymbolTableNode", "kind": "Mdef", "node": {".class": "FuncDef", "arg_kinds": [0, 0, 4], "arg_names": ["self", "config_key", "kwargs"], "flags": [], "fullname": "simple_playgrounds.elements.collection.zone.TerminationZone.__init__", "name": "__init__", "type": null}}, "activate": {".class": "SymbolTableNode", "kind": "Mdef", "node": {".class": "FuncDef", "arg_kinds": [0, 2], "arg_names": ["self", "args"], "flags": [], "fullname": "simple_playgrounds.elements.collection.zone.TerminationZone.activate", "name": "activate", "type": null}}, "terminate_upon_activation": {".class": "SymbolTableNode", "kind": "Mdef", "node": {".class": "Decorator", "func": {".class": "FuncDef", "arg_kinds": [0], "arg_names": ["self"], "flags": ["is_property", "is_decorated"], "fullname": "simple_playgrounds.elements.collection.zone.TerminationZone.terminate_upon_activation", "name": "terminate_upon_activation", "type": null}, "is_overload": false, "var": {".class": "Var", "flags": ["is_initialized_in_class", "is_property", "is_ready"], "fullname": null, "name": "terminate_upon_activation", "type": {".class": "CallableType", "arg_kinds": [0], "arg_names": ["self"], "arg_types": ["simple_playgrounds.elements.collection.zone.TerminationZone"], "bound_args": [], "def_extras": {}, "fallback": "builtins.function", "implicit": true, "is_ellipsis_args": false, "name": "terminate_upon_activation of TerminationZone", "ret_type": {".class": "AnyType", "missing_import_name": null, "source_any": null, "type_of_any": 1}, "variables": []}}}}}, "tuple_type": null, "type_vars": [], "typeddict_type": null}}, "ToxicZone": {".class": "SymbolTableNode", "kind": "Gdef", "node": {".class": "TypeInfo", "_promote": null, "abstract_attributes": [], "bases": ["simple_playgrounds.elements.collection.zone.RewardZone"], "declared_metaclass": null, "defn": {".class": "ClassDef", "fullname": "simple_playgrounds.elements.collection.zone.ToxicZone", "name": "ToxicZone", "type_vars": []}, "flags": [], "fullname": "simple_playgrounds.elements.collection.zone.ToxicZone", "metaclass_type": "abc.ABCMeta", "metadata": {}, "module_name": "simple_playgrounds.elements.collection.zone", "mro": ["simple_playgrounds.elements.collection.zone.ToxicZone", "simple_playgrounds.elements.collection.zone.RewardZone", "simple_playgrounds.elements.element.ZoneElement", "simple_playgrounds.elements.element.InteractiveElement", "simple_playgrounds.elements.element.SceneElement", "simple_playgrounds.common.entity.Entity", "abc.ABC", "builtins.object"], "names": {".class": "SymbolTable", "__init__": {".class": "SymbolTableNode", "kind": "Mdef", "node": {".class": "FuncDef", "arg_kinds": [0, 0, 0, 4], "arg_names": ["self", "reward", "limit", "entity_params"], "flags": [], "fullname": "simple_playgrounds.elements.collection.zone.ToxicZone.__init__", "name": "__init__", "type": {".class": "CallableType", "arg_kinds": [0, 0, 0, 4], "arg_names": ["self", "reward", "limit", "entity_params"], "arg_types": ["simple_playgrounds.elements.collection.zone.ToxicZone", "builtins.float", {".class": "UnionType", "items": ["builtins.float", {".class": "NoneType"}]}, {".class": "AnyType", "missing_import_name": null, "source_any": null, "type_of_any": 1}], "bound_args": [], "def_extras": {"first_arg": "self"}, "fallback": "builtins.function", "implicit": false, "is_ellipsis_args": false, "name": "__init__ of ToxicZone", "ret_type": {".class": "NoneType"}, "variables": []}}}}, "tuple_type": null, "type_vars": [], "typeddict_type": null}}, "ZoneElement": {".class": "SymbolTableNode", "cross_ref": "simple_playgrounds.elements.element.ZoneElement", "kind": "Gdef"}, "__doc__": {".class": "SymbolTableNode", "kind": "Gdef", "node": {".class": "Var", "flags": ["is_ready"], "fullname": "simple_playgrounds.elements.collection.zone.__doc__", "name": "__doc__", "type": "builtins.str"}}, "__file__": {".class": "SymbolTableNode", "kind": "Gdef", "node": {".class": "Var", "flags": ["is_ready"], "fullname": "simple_playgrounds.elements.collection.zone.__file__", "name": "__file__", "type": "builtins.str"}}, "__name__": {".class": "SymbolTableNode", "kind": "Gdef", "node": {".class": "Var", "flags": ["is_ready"], "fullname": "simple_playgrounds.elements.collection.zone.__name__", "name": "__name__", "type": "builtins.str"}}, "__package__": {".class": "SymbolTableNode", "kind": "Gdef", "node": {".class": "Var", "flags": ["is_ready"], "fullname": "simple_playgrounds.elements.collection.zone.__package__", "name": "__package__", "type": "builtins.str"}}, "parse_configuration": {".class": "SymbolTableNode", "cross_ref": "simple_playgrounds.configs.parser.parse_configuration", "kind": "Gdef"}}, "path": "/home/michael/PycharmProjects/simple-playgrounds/simple_playgrounds/elements/collection/zone.py"}