{".class": "MypyFile", "_fullname": "simple_playgrounds.playgrounds.collection.rl.basic", "is_partial_stub_package": false, "is_stub": false, "names": {".class": "SymbolTable", "Coin": {".class": "SymbolTableNode", "cross_ref": "simple_playgrounds.elements.collection.gem.Coin", "kind": "Gdef"}, "CoinMaster": {".class": "SymbolTableNode", "kind": "Gdef", "node": {".class": "TypeInfo", "_promote": null, "abstract_attributes": [], "bases": ["simple_playgrounds.playgrounds.layouts.SingleRoom"], "declared_metaclass": null, "defn": {".class": "ClassDef", "fullname": "simple_playgrounds.playgrounds.collection.rl.basic.CoinMaster", "name": "CoinMaster", "type_vars": []}, "flags": [], "fullname": "simple_playgrounds.playgrounds.collection.rl.basic.CoinMaster", "metaclass_type": "abc.ABCMeta", "metadata": {}, "module_name": "simple_playgrounds.playgrounds.collection.rl.basic", "mro": ["simple_playgrounds.playgrounds.collection.rl.basic.CoinMaster", "simple_playgrounds.playgrounds.layouts.SingleRoom", "simple_playgrounds.playgrounds.layouts.GridRooms", "simple_playgrounds.playgrounds.playground.Playground", "abc.ABC", "builtins.object"], "names": {".class": "SymbolTable", "__init__": {".class": "SymbolTableNode", "kind": "Mdef", "node": {".class": "FuncDef", "arg_kinds": [0], "arg_names": ["self"], "flags": [], "fullname": "simple_playgrounds.playgrounds.collection.rl.basic.CoinMaster.__init__", "name": "__init__", "type": null}}, "_assign_areas": {".class": "SymbolTableNode", "kind": "Mdef", "node": {".class": "FuncDef", "arg_kinds": [0], "arg_names": ["self"], "flags": [], "fullname": "simple_playgrounds.playgrounds.collection.rl.basic.CoinMaster._assign_areas", "name": "_assign_areas", "type": null}}, "_fields_produce": {".class": "SymbolTableNode", "kind": "Mdef", "node": {".class": "FuncDef", "arg_kinds": [0], "arg_names": ["self"], "flags": [], "fullname": "simple_playgrounds.playgrounds.collection.rl.basic.CoinMaster._fields_produce", "name": "_fields_produce", "type": null}}, "agent_starting_area": {".class": "SymbolTableNode", "implicit": true, "kind": "Mdef", "node": {".class": "Var", "flags": [], "fullname": "simple_playgrounds.playgrounds.collection.rl.basic.CoinMaster.agent_starting_area", "name": "agent_starting_area", "type": {".class": "AnyType", "missing_import_name": null, "source_any": null, "type_of_any": 1}}}, "area_prod": {".class": "SymbolTableNode", "implicit": true, "kind": "Mdef", "node": {".class": "Var", "flags": [], "fullname": "simple_playgrounds.playgrounds.collection.rl.basic.CoinMaster.area_prod", "name": "area_prod", "type": {".class": "AnyType", "missing_import_name": null, "source_any": null, "type_of_any": 1}}}, "area_vending": {".class": "SymbolTableNode", "implicit": true, "kind": "Mdef", "node": {".class": "Var", "flags": [], "fullname": "simple_playgrounds.playgrounds.collection.rl.basic.CoinMaster.area_vending", "name": "area_vending", "type": {".class": "AnyType", "missing_import_name": null, "source_any": null, "type_of_any": 1}}}, "field": {".class": "SymbolTableNode", "implicit": true, "kind": "Mdef", "node": {".class": "Var", "flags": [], "fullname": "simple_playgrounds.playgrounds.collection.rl.basic.CoinMaster.field", "name": "field", "type": {".class": "AnyType", "missing_import_name": null, "source_any": null, "type_of_any": 1}}}, "reset": {".class": "SymbolTableNode", "kind": "Mdef", "node": {".class": "FuncDef", "arg_kinds": [0], "arg_names": ["self"], "flags": [], "fullname": "simple_playgrounds.playgrounds.collection.rl.basic.CoinMaster.reset", "name": "reset", "type": null}}, "vending_machine": {".class": "SymbolTableNode", "implicit": true, "kind": "Mdef", "node": {".class": "Var", "flags": [], "fullname": "simple_playgrounds.playgrounds.collection.rl.basic.CoinMaster.vending_machine", "name": "vending_machine", "type": {".class": "AnyType", "missing_import_name": null, "source_any": null, "type_of_any": 1}}}}, "tuple_type": null, "type_vars": [], "typeddict_type": null}}, "CoordinateSampler": {".class": "SymbolTableNode", "cross_ref": "simple_playgrounds.common.position_samplers.CoordinateSampler", "kind": "Gdef"}, "Field": {".class": "SymbolTableNode", "cross_ref": "simple_playgrounds.elements.field.Field", "kind": "Gdef"}, "PlaygroundRegister": {".class": "SymbolTableNode", "cross_ref": "simple_playgrounds.playgrounds.playground.PlaygroundRegister", "kind": "Gdef"}, "SingleRoom": {".class": "SymbolTableNode", "cross_ref": "simple_playgrounds.playgrounds.layouts.SingleRoom", "kind": "Gdef"}, "VendingMachine": {".class": "SymbolTableNode", "cross_ref": "simple_playgrounds.elements.collection.interactive.VendingMachine", "kind": "Gdef"}, "__doc__": {".class": "SymbolTableNode", "kind": "Gdef", "node": {".class": "Var", "flags": ["is_ready"], "fullname": "simple_playgrounds.playgrounds.collection.rl.basic.__doc__", "name": "__doc__", "type": "builtins.str"}}, "__file__": {".class": "SymbolTableNode", "kind": "Gdef", "node": {".class": "Var", "flags": ["is_ready"], "fullname": "simple_playgrounds.playgrounds.collection.rl.basic.__file__", "name": "__file__", "type": "builtins.str"}}, "__name__": {".class": "SymbolTableNode", "kind": "Gdef", "node": {".class": "Var", "flags": ["is_ready"], "fullname": "simple_playgrounds.playgrounds.collection.rl.basic.__name__", "name": "__name__", "type": "builtins.str"}}, "__package__": {".class": "SymbolTableNode", "kind": "Gdef", "node": {".class": "Var", "flags": ["is_ready"], "fullname": "simple_playgrounds.playgrounds.collection.rl.basic.__package__", "name": "__package__", "type": "builtins.str"}}, "random": {".class": "SymbolTableNode", "cross_ref": "random", "kind": "Gdef"}}, "path": "/home/michael/PycharmProjects/simple-playgrounds/simple_playgrounds/playgrounds/collection/rl/basic.py"}