{".class": "MypyFile", "_fullname": "pymunk", "is_partial_stub_package": false, "is_stub": false, "names": {".class": "SymbolTable", "Arbiter": {".class": "SymbolTableNode", "cross_ref": "pymunk.arbiter.Arbiter", "kind": "Gdef"}, "BB": {".class": "SymbolTableNode", "cross_ref": "pymunk.bb.BB", "kind": "Gdef"}, "Body": {".class": "SymbolTableNode", "cross_ref": "pymunk.body.Body", "kind": "Gdef"}, "Circle": {".class": "SymbolTableNode", "cross_ref": "pymunk.shapes.Circle", "kind": "Gdef"}, "CollisionHandler": {".class": "SymbolTableNode", "cross_ref": "pymunk.collision_handler.CollisionHandler", "kind": "Gdef"}, "Constraint": {".class": "SymbolTableNode", "cross_ref": "pymunk.constraints.Constraint", "kind": "Gdef", "module_public": false}, "ContactPoint": {".class": "SymbolTableNode", "cross_ref": "pymunk.contact_point_set.ContactPoint", "kind": "Gdef"}, "ContactPointSet": {".class": "SymbolTableNode", "cross_ref": "pymunk.contact_point_set.ContactPointSet", "kind": "Gdef"}, "DampedRotarySpring": {".class": "SymbolTableNode", "cross_ref": "pymunk.constraints.DampedRotarySpring", "kind": "Gdef", "module_public": false}, "DampedSpring": {".class": "SymbolTableNode", "cross_ref": "pymunk.constraints.DampedSpring", "kind": "Gdef", "module_public": false}, "GearJoint": {".class": "SymbolTableNode", "cross_ref": "pymunk.constraints.GearJoint", "kind": "Gdef", "module_public": false}, "GrooveJoint": {".class": "SymbolTableNode", "cross_ref": "pymunk.constraints.GrooveJoint", "kind": "Gdef", "module_public": false}, "PinJoint": {".class": "SymbolTableNode", "cross_ref": "pymunk.constraints.PinJoint", "kind": "Gdef", "module_public": false}, "PivotJoint": {".class": "SymbolTableNode", "cross_ref": "pymunk.constraints.PivotJoint", "kind": "Gdef", "module_public": false}, "PointQueryInfo": {".class": "SymbolTableNode", "cross_ref": "pymunk.query_info.PointQueryInfo", "kind": "Gdef"}, "Poly": {".class": "SymbolTableNode", "cross_ref": "pymunk.shapes.Poly", "kind": "Gdef"}, "RatchetJoint": {".class": "SymbolTableNode", "cross_ref": "pymunk.constraints.RatchetJoint", "kind": "Gdef", "module_public": false}, "RotaryLimitJoint": {".class": "SymbolTableNode", "cross_ref": "pymunk.constraints.RotaryLimitJoint", "kind": "Gdef", "module_public": false}, "Segment": {".class": "SymbolTableNode", "cross_ref": "pymunk.shapes.Segment", "kind": "Gdef"}, "SegmentQueryInfo": {".class": "SymbolTableNode", "cross_ref": "pymunk.query_info.SegmentQueryInfo", "kind": "Gdef"}, "Sequence": {".class": "SymbolTableNode", "cross_ref": "typing.Sequence", "kind": "Gdef", "module_public": false}, "Shape": {".class": "SymbolTableNode", "cross_ref": "pymunk.shapes.Shape", "kind": "Gdef"}, "ShapeFilter": {".class": "SymbolTableNode", "cross_ref": "pymunk.shape_filter.ShapeFilter", "kind": "Gdef"}, "ShapeQueryInfo": {".class": "SymbolTableNode", "cross_ref": "pymunk.query_info.ShapeQueryInfo", "kind": "Gdef"}, "SimpleMotor": {".class": "SymbolTableNode", "cross_ref": "pymunk.constraints.SimpleMotor", "kind": "Gdef", "module_public": false}, "SlideJoint": {".class": "SymbolTableNode", "cross_ref": "pymunk.constraints.SlideJoint", "kind": "Gdef", "module_public": false}, "Space": {".class": "SymbolTableNode", "cross_ref": "pymunk.space.Space", "kind": "Gdef"}, "SpaceDebugDrawOptions": {".class": "SymbolTableNode", "cross_ref": "pymunk.space_debug_draw_options.SpaceDebugDrawOptions", "kind": "Gdef"}, "Transform": {".class": "SymbolTableNode", "cross_ref": "pymunk.transform.Transform", "kind": "Gdef"}, "Tuple": {".class": "SymbolTableNode", "cross_ref": "typing.Tuple", "kind": "Gdef", "module_public": false}, "Vec2d": {".class": "SymbolTableNode", "cross_ref": "pymunk.vec2d.Vec2d", "kind": "Gdef"}, "__all__": {".class": "SymbolTableNode", "kind": "Gdef", "module_public": false, "node": {".class": "Var", "flags": [], "fullname": "pymunk.__all__", "name": "__all__", "type": {".class": "Instance", "args": ["builtins.str"], "type_ref": "builtins.list"}}}, "__doc__": {".class": "SymbolTableNode", "kind": "Gdef", "module_public": false, "node": {".class": "Var", "flags": ["is_ready"], "fullname": "pymunk.__doc__", "name": "__doc__", "type": "builtins.str"}}, "__docformat__": {".class": "SymbolTableNode", "kind": "Gdef", "module_public": false, "node": {".class": "Var", "flags": ["is_ready"], "fullname": "pymunk.__docformat__", "name": "__docformat__", "type": "builtins.str"}}, "__file__": {".class": "SymbolTableNode", "kind": "Gdef", "module_public": false, "node": {".class": "Var", "flags": ["is_ready"], "fullname": "pymunk.__file__", "name": "__file__", "type": "builtins.str"}}, "__name__": {".class": "SymbolTableNode", "kind": "Gdef", "module_public": false, "node": {".class": "Var", "flags": ["is_ready"], "fullname": "pymunk.__name__", "name": "__name__", "type": "builtins.str"}}, "__package__": {".class": "SymbolTableNode", "kind": "Gdef", "module_public": false, "node": {".class": "Var", "flags": ["is_ready"], "fullname": "pymunk.__package__", "name": "__package__", "type": "builtins.str"}}, "_chipmunk_cffi": {".class": "SymbolTableNode", "cross_ref": "pymunk._chipmunk_cffi", "kind": "Gdef", "module_public": false}, "_version": {".class": "SymbolTableNode", "cross_ref": "pymunk._version", "kind": "Gdef", "module_public": false}, "area_for_circle": {".class": "SymbolTableNode", "kind": "Gdef", "module_public": false, "node": {".class": "FuncDef", "arg_kinds": [0, 0], "arg_names": ["inner_radius", "outer_radius"], "flags": [], "fullname": "pymunk.area_for_circle", "name": "area_for_circle", "type": {".class": "CallableType", "arg_kinds": [0, 0], "arg_names": ["inner_radius", "outer_radius"], "arg_types": ["builtins.float", "builtins.float"], "bound_args": [], "def_extras": {"first_arg": null}, "fallback": "builtins.function", "implicit": false, "is_ellipsis_args": false, "name": "area_for_circle", "ret_type": "builtins.float", "variables": []}}}, "area_for_poly": {".class": "SymbolTableNode", "kind": "Gdef", "module_public": false, "node": {".class": "FuncDef", "arg_kinds": [0, 1], "arg_names": ["vertices", "radius"], "flags": [], "fullname": "pymunk.area_for_poly", "name": "area_for_poly", "type": {".class": "CallableType", "arg_kinds": [0, 1], "arg_names": ["vertices", "radius"], "arg_types": [{".class": "Instance", "args": [{".class": "TupleType", "implicit": false, "items": ["builtins.float", "builtins.float"], "partial_fallback": {".class": "Instance", "args": [{".class": "AnyType", "missing_import_name": null, "source_any": null, "type_of_any": 6}], "type_ref": "builtins.tuple"}}], "type_ref": "typing.Sequence"}, "builtins.float"], "bound_args": [], "def_extras": {"first_arg": null}, "fallback": "builtins.function", "implicit": false, "is_ellipsis_args": false, "name": "area_for_poly", "ret_type": "builtins.float", "variables": []}}}, "area_for_segment": {".class": "SymbolTableNode", "kind": "Gdef", "module_public": false, "node": {".class": "FuncDef", "arg_kinds": [0, 0, 0], "arg_names": ["a", "b", "radius"], "flags": [], "fullname": "pymunk.area_for_segment", "name": "area_for_segment", "type": {".class": "CallableType", "arg_kinds": [0, 0, 0], "arg_names": ["a", "b", "radius"], "arg_types": [{".class": "TupleType", "implicit": false, "items": ["builtins.float", "builtins.float"], "partial_fallback": {".class": "Instance", "args": [{".class": "AnyType", "missing_import_name": null, "source_any": null, "type_of_any": 6}], "type_ref": "builtins.tuple"}}, {".class": "TupleType", "implicit": false, "items": ["builtins.float", "builtins.float"], "partial_fallback": {".class": "Instance", "args": [{".class": "AnyType", "missing_import_name": null, "source_any": null, "type_of_any": 6}], "type_ref": "builtins.tuple"}}, "builtins.float"], "bound_args": [], "def_extras": {"first_arg": null}, "fallback": "builtins.function", "implicit": false, "is_ellipsis_args": false, "name": "area_for_segment", "ret_type": "builtins.float", "variables": []}}}, "cast": {".class": "SymbolTableNode", "cross_ref": "typing.cast", "kind": "Gdef", "module_public": false}, "chipmunk_version": {".class": "SymbolTableNode", "kind": "Gdef", "node": {".class": "Var", "flags": ["is_ready"], "fullname": "pymunk.chipmunk_version", "name": "chipmunk_version", "type": "builtins.str"}}, "cp": {".class": "SymbolTableNode", "kind": "Gdef", "module_public": false, "node": {".class": "Var", "flags": [], "fullname": "pymunk.cp", "name": "cp", "type": {".class": "AnyType", "missing_import_name": "pymunk._chipmunk_cffi.lib", "source_any": null, "type_of_any": 3}}}, "ffi": {".class": "SymbolTableNode", "kind": "Gdef", "module_public": false, "node": {".class": "Var", "flags": [], "fullname": "pymunk.ffi", "name": "ffi", "type": {".class": "AnyType", "missing_import_name": "pymunk._chipmunk_cffi.ffi", "source_any": null, "type_of_any": 3}}}, "moment_for_box": {".class": "SymbolTableNode", "kind": "Gdef", "node": {".class": "FuncDef", "arg_kinds": [0, 0], "arg_names": ["mass", "size"], "flags": [], "fullname": "pymunk.moment_for_box", "name": "moment_for_box", "type": {".class": "CallableType", "arg_kinds": [0, 0], "arg_names": ["mass", "size"], "arg_types": ["builtins.float", {".class": "TupleType", "implicit": false, "items": ["builtins.float", "builtins.float"], "partial_fallback": {".class": "Instance", "args": [{".class": "AnyType", "missing_import_name": null, "source_any": null, "type_of_any": 6}], "type_ref": "builtins.tuple"}}], "bound_args": [], "def_extras": {"first_arg": null}, "fallback": "builtins.function", "implicit": false, "is_ellipsis_args": false, "name": "moment_for_box", "ret_type": "builtins.float", "variables": []}}}, "moment_for_circle": {".class": "SymbolTableNode", "kind": "Gdef", "node": {".class": "FuncDef", "arg_kinds": [0, 0, 0, 1], "arg_names": ["mass", "inner_radius", "outer_radius", "offset"], "flags": [], "fullname": "pymunk.moment_for_circle", "name": "moment_for_circle", "type": {".class": "CallableType", "arg_kinds": [0, 0, 0, 1], "arg_names": ["mass", "inner_radius", "outer_radius", "offset"], "arg_types": ["builtins.float", "builtins.float", "builtins.float", {".class": "TupleType", "implicit": false, "items": ["builtins.float", "builtins.float"], "partial_fallback": {".class": "Instance", "args": [{".class": "AnyType", "missing_import_name": null, "source_any": null, "type_of_any": 6}], "type_ref": "builtins.tuple"}}], "bound_args": [], "def_extras": {"first_arg": null}, "fallback": "builtins.function", "implicit": false, "is_ellipsis_args": false, "name": "moment_for_circle", "ret_type": "builtins.float", "variables": []}}}, "moment_for_poly": {".class": "SymbolTableNode", "kind": "Gdef", "node": {".class": "FuncDef", "arg_kinds": [0, 0, 1, 1], "arg_names": ["mass", "vertices", "offset", "radius"], "flags": [], "fullname": "pymunk.moment_for_poly", "name": "moment_for_poly", "type": {".class": "CallableType", "arg_kinds": [0, 0, 1, 1], "arg_names": ["mass", "vertices", "offset", "radius"], "arg_types": ["builtins.float", {".class": "Instance", "args": [{".class": "TupleType", "implicit": false, "items": ["builtins.float", "builtins.float"], "partial_fallback": {".class": "Instance", "args": [{".class": "AnyType", "missing_import_name": null, "source_any": null, "type_of_any": 6}], "type_ref": "builtins.tuple"}}], "type_ref": "typing.Sequence"}, {".class": "TupleType", "implicit": false, "items": ["builtins.float", "builtins.float"], "partial_fallback": {".class": "Instance", "args": [{".class": "AnyType", "missing_import_name": null, "source_any": null, "type_of_any": 6}], "type_ref": "builtins.tuple"}}, "builtins.float"], "bound_args": [], "def_extras": {"first_arg": null}, "fallback": "builtins.function", "implicit": false, "is_ellipsis_args": false, "name": "moment_for_poly", "ret_type": "builtins.float", "variables": []}}}, "moment_for_segment": {".class": "SymbolTableNode", "kind": "Gdef", "node": {".class": "FuncDef", "arg_kinds": [0, 0, 0, 0], "arg_names": ["mass", "a", "b", "radius"], "flags": [], "fullname": "pymunk.moment_for_segment", "name": "moment_for_segment", "type": {".class": "CallableType", "arg_kinds": [0, 0, 0, 0], "arg_names": ["mass", "a", "b", "radius"], "arg_types": ["builtins.float", {".class": "TupleType", "implicit": false, "items": ["builtins.float", "builtins.float"], "partial_fallback": {".class": "Instance", "args": [{".class": "AnyType", "missing_import_name": null, "source_any": null, "type_of_any": 6}], "type_ref": "builtins.tuple"}}, {".class": "TupleType", "implicit": false, "items": ["builtins.float", "builtins.float"], "partial_fallback": {".class": "Instance", "args": [{".class": "AnyType", "missing_import_name": null, "source_any": null, "type_of_any": 6}], "type_ref": "builtins.tuple"}}, "builtins.float"], "bound_args": [], "def_extras": {"first_arg": null}, "fallback": "builtins.function", "implicit": false, "is_ellipsis_args": false, "name": "moment_for_segment", "ret_type": "builtins.float", "variables": []}}}, "version": {".class": "SymbolTableNode", "kind": "Gdef", "node": {".class": "Var", "flags": ["is_ready"], "fullname": "pymunk.version", "name": "version", "type": "builtins.str"}}}, "path": "/home/michael/anaconda3/envs/simple-playgrounds/lib/python3.7/site-packages/pymunk/__init__.py"}