{".class": "MypyFile", "_fullname": "pymunk.transform", "is_partial_stub_package": false, "is_stub": false, "names": {".class": "SymbolTable", "NamedTuple": {".class": "SymbolTableNode", "cross_ref": "typing.NamedTuple", "kind": "Gdef"}, "Transform": {".class": "SymbolTableNode", "kind": "Gdef", "node": {".class": "TypeInfo", "_promote": null, "abstract_attributes": [], "bases": [{".class": "Instance", "args": ["builtins.float"], "type_ref": "builtins.tuple"}], "declared_metaclass": null, "defn": {".class": "ClassDef", "fullname": "pymunk.transform.Transform", "name": "Transform", "type_vars": []}, "flags": ["is_named_tuple"], "fullname": "pymunk.transform.Transform", "metaclass_type": null, "metadata": {"namedtuple": {"fields": ["a", "b", "c", "d", "tx", "ty"]}}, "module_name": "pymunk.transform", "mro": ["pymunk.transform.Transform", "builtins.tuple", "typing.Sequence", "typing.Collection", "typing.Reversible", "typing.Iterable", "typing.Container", "builtins.object"], "names": {".class": "SymbolTable", "_NT": {".class": "SymbolTableNode", "kind": "Mdef", "node": {".class": "TypeVarExpr", "fullname": "pymunk.transform.Transform._NT", "name": "_NT", "upper_bound": {".class": "TupleType", "implicit": false, "items": ["builtins.float", "builtins.float", "builtins.float", "builtins.float", "builtins.float", "builtins.float"], "partial_fallback": {".class": "Instance", "args": ["builtins.float"], "type_ref": "builtins.tuple"}}, "values": [], "variance": 0}}, "__annotations__": {".class": "SymbolTableNode", "kind": "Mdef", "node": {".class": "Var", "flags": ["is_initialized_in_class", "is_ready"], "fullname": "pymunk.transform.Transform.__annotations__", "name": "__annotations__", "type": {".class": "Instance", "args": ["builtins.str", {".class": "AnyType", "missing_import_name": null, "source_any": null, "type_of_any": 6}], "type_ref": "builtins.dict"}}}, "__doc__": {".class": "SymbolTableNode", "kind": "Mdef", "node": {".class": "Var", "flags": ["is_initialized_in_class", "is_ready"], "fullname": "pymunk.transform.Transform.__doc__", "name": "__doc__", "type": "builtins.str"}}, "__new__": {".class": "SymbolTableNode", "kind": "Mdef", "node": {".class": "FuncDef", "arg_kinds": [0, 1, 1, 1, 1, 1, 1], "arg_names": ["_cls", "a", "b", "c", "d", "tx", "ty"], "flags": [], "fullname": "pymunk.transform.Transform.__new__", "name": "__new__", "type": {".class": "CallableType", "arg_kinds": [0, 1, 1, 1, 1, 1, 1], "arg_names": ["_cls", "a", "b", "c", "d", "tx", "ty"], "arg_types": [{".class": "TypeType", "item": {".class": "TypeVarType", "fullname": "pymunk.transform.Transform._NT", "id": -1, "name": "_NT", "upper_bound": {".class": "TupleType", "implicit": false, "items": ["builtins.float", "builtins.float", "builtins.float", "builtins.float", "builtins.float", "builtins.float"], "partial_fallback": {".class": "Instance", "args": ["builtins.float"], "type_ref": "builtins.tuple"}}, "values": [], "variance": 0}}, "builtins.float", "builtins.float", "builtins.float", "builtins.float", "builtins.float", "builtins.float"], "bound_args": [], "def_extras": {}, "fallback": "builtins.function", "implicit": false, "is_ellipsis_args": false, "name": "__new__ of Transform", "ret_type": {".class": "TypeVarType", "fullname": "pymunk.transform.Transform._NT", "id": -1, "name": "_NT", "upper_bound": {".class": "TupleType", "implicit": false, "items": ["builtins.float", "builtins.float", "builtins.float", "builtins.float", "builtins.float", "builtins.float"], "partial_fallback": {".class": "Instance", "args": ["builtins.float"], "type_ref": "builtins.tuple"}}, "values": [], "variance": 0}, "variables": [{".class": "TypeVarDef", "fullname": "pymunk.transform.Transform._NT", "id": -1, "name": "_NT", "upper_bound": {".class": "TupleType", "implicit": false, "items": ["builtins.float", "builtins.float", "builtins.float", "builtins.float", "builtins.float", "builtins.float"], "partial_fallback": {".class": "Instance", "args": ["builtins.float"], "type_ref": "builtins.tuple"}}, "values": [], "variance": 0}]}}, "plugin_generated": true}, "_asdict": {".class": "SymbolTableNode", "kind": "Mdef", "node": {".class": "FuncDef", "arg_kinds": [0], "arg_names": ["_self"], "flags": [], "fullname": "pymunk.transform.Transform._asdict", "name": "_asdict", "type": {".class": "CallableType", "arg_kinds": [0], "arg_names": ["_self"], "arg_types": [{".class": "TypeVarType", "fullname": "pymunk.transform.Transform._NT", "id": -1, "name": "_NT", "upper_bound": {".class": "TupleType", "implicit": false, "items": ["builtins.float", "builtins.float", "builtins.float", "builtins.float", "builtins.float", "builtins.float"], "partial_fallback": {".class": "Instance", "args": ["builtins.float"], "type_ref": "builtins.tuple"}}, "values": [], "variance": 0}], "bound_args": [], "def_extras": {}, "fallback": "builtins.function", "implicit": false, "is_ellipsis_args": false, "name": "_asdict of Transform", "ret_type": {".class": "Instance", "args": ["builtins.str", {".class": "AnyType", "missing_import_name": null, "source_any": null, "type_of_any": 6}], "type_ref": "builtins.dict"}, "variables": [{".class": "TypeVarDef", "fullname": "pymunk.transform.Transform._NT", "id": -1, "name": "_NT", "upper_bound": {".class": "TupleType", "implicit": false, "items": ["builtins.float", "builtins.float", "builtins.float", "builtins.float", "builtins.float", "builtins.float"], "partial_fallback": {".class": "Instance", "args": ["builtins.float"], "type_ref": "builtins.tuple"}}, "values": [], "variance": 0}]}}, "plugin_generated": true}, "_field_defaults": {".class": "SymbolTableNode", "kind": "Mdef", "node": {".class": "Var", "flags": ["is_initialized_in_class", "is_ready"], "fullname": "pymunk.transform.Transform._field_defaults", "name": "_field_defaults", "type": {".class": "Instance", "args": ["builtins.str", {".class": "AnyType", "missing_import_name": null, "source_any": null, "type_of_any": 6}], "type_ref": "builtins.dict"}}}, "_field_types": {".class": "SymbolTableNode", "kind": "Mdef", "node": {".class": "Var", "flags": ["is_initialized_in_class", "is_ready"], "fullname": "pymunk.transform.Transform._field_types", "name": "_field_types", "type": {".class": "Instance", "args": ["builtins.str", {".class": "AnyType", "missing_import_name": null, "source_any": null, "type_of_any": 6}], "type_ref": "builtins.dict"}}}, "_fields": {".class": "SymbolTableNode", "kind": "Mdef", "node": {".class": "Var", "flags": ["is_initialized_in_class", "is_ready"], "fullname": "pymunk.transform.Transform._fields", "name": "_fields", "type": {".class": "TupleType", "implicit": false, "items": ["builtins.str", "builtins.str", "builtins.str", "builtins.str", "builtins.str", "builtins.str"], "partial_fallback": {".class": "Instance", "args": [{".class": "AnyType", "missing_import_name": null, "source_any": null, "type_of_any": 6}], "type_ref": "builtins.tuple"}}}}, "_make": {".class": "SymbolTableNode", "kind": "Mdef", "node": {".class": "Decorator", "func": {".class": "FuncDef", "arg_kinds": [0, 0, 5, 5], "arg_names": ["_cls", "iterable", "new", "len"], "flags": ["is_class", "is_decorated"], "fullname": "pymunk.transform.Transform._make", "name": "_make", "type": {".class": "CallableType", "arg_kinds": [0, 0, 5, 5], "arg_names": ["_cls", "iterable", "new", "len"], "arg_types": [{".class": "TypeType", "item": {".class": "TypeVarType", "fullname": "pymunk.transform.Transform._NT", "id": -1, "name": "_NT", "upper_bound": {".class": "TupleType", "implicit": false, "items": ["builtins.float", "builtins.float", "builtins.float", "builtins.float", "builtins.float", "builtins.float"], "partial_fallback": {".class": "Instance", "args": ["builtins.float"], "type_ref": "builtins.tuple"}}, "values": [], "variance": 0}}, {".class": "Instance", "args": [{".class": "AnyType", "missing_import_name": null, "source_any": null, "type_of_any": 6}], "type_ref": "typing.Iterable"}, {".class": "AnyType", "missing_import_name": null, "source_any": null, "type_of_any": 6}, {".class": "AnyType", "missing_import_name": null, "source_any": null, "type_of_any": 6}], "bound_args": [], "def_extras": {}, "fallback": "builtins.function", "implicit": false, "is_ellipsis_args": false, "name": "_make of Transform", "ret_type": {".class": "TypeVarType", "fullname": "pymunk.transform.Transform._NT", "id": -1, "name": "_NT", "upper_bound": {".class": "TupleType", "implicit": false, "items": ["builtins.float", "builtins.float", "builtins.float", "builtins.float", "builtins.float", "builtins.float"], "partial_fallback": {".class": "Instance", "args": ["builtins.float"], "type_ref": "builtins.tuple"}}, "values": [], "variance": 0}, "variables": [{".class": "TypeVarDef", "fullname": "pymunk.transform.Transform._NT", "id": -1, "name": "_NT", "upper_bound": {".class": "TupleType", "implicit": false, "items": ["builtins.float", "builtins.float", "builtins.float", "builtins.float", "builtins.float", "builtins.float"], "partial_fallback": {".class": "Instance", "args": ["builtins.float"], "type_ref": "builtins.tuple"}}, "values": [], "variance": 0}]}}, "is_overload": false, "var": {".class": "Var", "flags": ["is_classmethod", "is_ready"], "fullname": "pymunk.transform.Transform._make", "name": "_make", "type": {".class": "CallableType", "arg_kinds": [0, 0, 5, 5], "arg_names": ["_cls", "iterable", "new", "len"], "arg_types": [{".class": "TypeType", "item": {".class": "TypeVarType", "fullname": "pymunk.transform.Transform._NT", "id": -1, "name": "_NT", "upper_bound": {".class": "TupleType", "implicit": false, "items": ["builtins.float", "builtins.float", "builtins.float", "builtins.float", "builtins.float", "builtins.float"], "partial_fallback": {".class": "Instance", "args": ["builtins.float"], "type_ref": "builtins.tuple"}}, "values": [], "variance": 0}}, {".class": "Instance", "args": [{".class": "AnyType", "missing_import_name": null, "source_any": null, "type_of_any": 6}], "type_ref": "typing.Iterable"}, {".class": "AnyType", "missing_import_name": null, "source_any": null, "type_of_any": 6}, {".class": "AnyType", "missing_import_name": null, "source_any": null, "type_of_any": 6}], "bound_args": [], "def_extras": {}, "fallback": "builtins.function", "implicit": false, "is_ellipsis_args": false, "name": "_make of Transform", "ret_type": {".class": "TypeVarType", "fullname": "pymunk.transform.Transform._NT", "id": -1, "name": "_NT", "upper_bound": {".class": "TupleType", "implicit": false, "items": ["builtins.float", "builtins.float", "builtins.float", "builtins.float", "builtins.float", "builtins.float"], "partial_fallback": {".class": "Instance", "args": ["builtins.float"], "type_ref": "builtins.tuple"}}, "values": [], "variance": 0}, "variables": [{".class": "TypeVarDef", "fullname": "pymunk.transform.Transform._NT", "id": -1, "name": "_NT", "upper_bound": {".class": "TupleType", "implicit": false, "items": ["builtins.float", "builtins.float", "builtins.float", "builtins.float", "builtins.float", "builtins.float"], "partial_fallback": {".class": "Instance", "args": ["builtins.float"], "type_ref": "builtins.tuple"}}, "values": [], "variance": 0}]}}}, "plugin_generated": true}, "_replace": {".class": "SymbolTableNode", "kind": "Mdef", "node": {".class": "FuncDef", "arg_kinds": [0, 5, 5, 5, 5, 5, 5], "arg_names": ["_self", "a", "b", "c", "d", "tx", "ty"], "flags": [], "fullname": "pymunk.transform.Transform._replace", "name": "_replace", "type": {".class": "CallableType", "arg_kinds": [0, 5, 5, 5, 5, 5, 5], "arg_names": ["_self", "a", "b", "c", "d", "tx", "ty"], "arg_types": [{".class": "TypeVarType", "fullname": "pymunk.transform.Transform._NT", "id": -1, "name": "_NT", "upper_bound": {".class": "TupleType", "implicit": false, "items": ["builtins.float", "builtins.float", "builtins.float", "builtins.float", "builtins.float", "builtins.float"], "partial_fallback": {".class": "Instance", "args": ["builtins.float"], "type_ref": "builtins.tuple"}}, "values": [], "variance": 0}, "builtins.float", "builtins.float", "builtins.float", "builtins.float", "builtins.float", "builtins.float"], "bound_args": [], "def_extras": {}, "fallback": "builtins.function", "implicit": false, "is_ellipsis_args": false, "name": "_replace of Transform", "ret_type": {".class": "TypeVarType", "fullname": "pymunk.transform.Transform._NT", "id": -1, "name": "_NT", "upper_bound": {".class": "TupleType", "implicit": false, "items": ["builtins.float", "builtins.float", "builtins.float", "builtins.float", "builtins.float", "builtins.float"], "partial_fallback": {".class": "Instance", "args": ["builtins.float"], "type_ref": "builtins.tuple"}}, "values": [], "variance": 0}, "variables": [{".class": "TypeVarDef", "fullname": "pymunk.transform.Transform._NT", "id": -1, "name": "_NT", "upper_bound": {".class": "TupleType", "implicit": false, "items": ["builtins.float", "builtins.float", "builtins.float", "builtins.float", "builtins.float", "builtins.float"], "partial_fallback": {".class": "Instance", "args": ["builtins.float"], "type_ref": "builtins.tuple"}}, "values": [], "variance": 0}]}}, "plugin_generated": true}, "_source": {".class": "SymbolTableNode", "kind": "Mdef", "node": {".class": "Var", "flags": ["is_initialized_in_class", "is_ready"], "fullname": "pymunk.transform.Transform._source", "name": "_source", "type": "builtins.str"}}, "a": {".class": "SymbolTableNode", "kind": "Mdef", "node": {".class": "Var", "flags": ["is_property", "is_ready"], "fullname": "pymunk.transform.Transform.a", "name": "a", "type": "builtins.float"}}, "a-redefinition": {".class": "SymbolTableNode", "cross_ref": "pymunk.transform.Transform.a", "kind": "Mdef"}, "b": {".class": "SymbolTableNode", "kind": "Mdef", "node": {".class": "Var", "flags": ["is_property", "is_ready"], "fullname": "pymunk.transform.Transform.b", "name": "b", "type": "builtins.float"}}, "b-redefinition": {".class": "SymbolTableNode", "cross_ref": "pymunk.transform.Transform.b", "kind": "Mdef"}, "c": {".class": "SymbolTableNode", "kind": "Mdef", "node": {".class": "Var", "flags": ["is_property", "is_ready"], "fullname": "pymunk.transform.Transform.c", "name": "c", "type": "builtins.float"}}, "c-redefinition": {".class": "SymbolTableNode", "cross_ref": "pymunk.transform.Transform.c", "kind": "Mdef"}, "d": {".class": "SymbolTableNode", "kind": "Mdef", "node": {".class": "Var", "flags": ["is_property", "is_ready"], "fullname": "pymunk.transform.Transform.d", "name": "d", "type": "builtins.float"}}, "d-redefinition": {".class": "SymbolTableNode", "cross_ref": "pymunk.transform.Transform.d", "kind": "Mdef"}, "identity": {".class": "SymbolTableNode", "kind": "Mdef", "node": {".class": "Decorator", "func": {".class": "FuncDef", "arg_kinds": [], "arg_names": [], "flags": ["is_static", "is_decorated"], "fullname": "pymunk.transform.Transform.identity", "name": "identity", "type": {".class": "CallableType", "arg_kinds": [], "arg_names": [], "arg_types": [], "bound_args": [], "def_extras": {"first_arg": null}, "fallback": "builtins.function", "implicit": false, "is_ellipsis_args": false, "name": "identity of Transform", "ret_type": {".class": "TupleType", "implicit": false, "items": ["builtins.float", "builtins.float", "builtins.float", "builtins.float", "builtins.float", "builtins.float"], "partial_fallback": "pymunk.transform.Transform"}, "variables": []}}, "is_overload": false, "var": {".class": "Var", "flags": ["is_initialized_in_class", "is_staticmethod", "is_ready"], "fullname": null, "name": "identity", "type": {".class": "CallableType", "arg_kinds": [], "arg_names": [], "arg_types": [], "bound_args": [], "def_extras": {"first_arg": null}, "fallback": "builtins.function", "implicit": false, "is_ellipsis_args": false, "name": "identity of Transform", "ret_type": {".class": "TupleType", "implicit": false, "items": ["builtins.float", "builtins.float", "builtins.float", "builtins.float", "builtins.float", "builtins.float"], "partial_fallback": "pymunk.transform.Transform"}, "variables": []}}}}, "rotation": {".class": "SymbolTableNode", "kind": "Mdef", "node": {".class": "Decorator", "func": {".class": "FuncDef", "arg_kinds": [0], "arg_names": ["t"], "flags": ["is_static", "is_decorated"], "fullname": "pymunk.transform.Transform.rotation", "name": "rotation", "type": {".class": "CallableType", "arg_kinds": [0], "arg_names": ["t"], "arg_types": ["builtins.float"], "bound_args": [], "def_extras": {"first_arg": null}, "fallback": "builtins.function", "implicit": false, "is_ellipsis_args": false, "name": "rotation of Transform", "ret_type": {".class": "TupleType", "implicit": false, "items": ["builtins.float", "builtins.float", "builtins.float", "builtins.float", "builtins.float", "builtins.float"], "partial_fallback": "pymunk.transform.Transform"}, "variables": []}}, "is_overload": false, "var": {".class": "Var", "flags": ["is_initialized_in_class", "is_staticmethod", "is_ready"], "fullname": null, "name": "rotation", "type": {".class": "CallableType", "arg_kinds": [0], "arg_names": ["t"], "arg_types": ["builtins.float"], "bound_args": [], "def_extras": {"first_arg": null}, "fallback": "builtins.function", "implicit": false, "is_ellipsis_args": false, "name": "rotation of Transform", "ret_type": {".class": "TupleType", "implicit": false, "items": ["builtins.float", "builtins.float", "builtins.float", "builtins.float", "builtins.float", "builtins.float"], "partial_fallback": "pymunk.transform.Transform"}, "variables": []}}}}, "scaling": {".class": "SymbolTableNode", "kind": "Mdef", "node": {".class": "Decorator", "func": {".class": "FuncDef", "arg_kinds": [0], "arg_names": ["s"], "flags": ["is_static", "is_decorated"], "fullname": "pymunk.transform.Transform.scaling", "name": "scaling", "type": {".class": "CallableType", "arg_kinds": [0], "arg_names": ["s"], "arg_types": ["builtins.float"], "bound_args": [], "def_extras": {"first_arg": null}, "fallback": "builtins.function", "implicit": false, "is_ellipsis_args": false, "name": "scaling of Transform", "ret_type": {".class": "TupleType", "implicit": false, "items": ["builtins.float", "builtins.float", "builtins.float", "builtins.float", "builtins.float", "builtins.float"], "partial_fallback": "pymunk.transform.Transform"}, "variables": []}}, "is_overload": false, "var": {".class": "Var", "flags": ["is_initialized_in_class", "is_staticmethod", "is_ready"], "fullname": null, "name": "scaling", "type": {".class": "CallableType", "arg_kinds": [0], "arg_names": ["s"], "arg_types": ["builtins.float"], "bound_args": [], "def_extras": {"first_arg": null}, "fallback": "builtins.function", "implicit": false, "is_ellipsis_args": false, "name": "scaling of Transform", "ret_type": {".class": "TupleType", "implicit": false, "items": ["builtins.float", "builtins.float", "builtins.float", "builtins.float", "builtins.float", "builtins.float"], "partial_fallback": "pymunk.transform.Transform"}, "variables": []}}}}, "translation": {".class": "SymbolTableNode", "kind": "Mdef", "node": {".class": "Decorator", "func": {".class": "FuncDef", "arg_kinds": [0, 0], "arg_names": ["x", "y"], "flags": ["is_static", "is_decorated"], "fullname": "pymunk.transform.Transform.translation", "name": "translation", "type": {".class": "CallableType", "arg_kinds": [0, 0], "arg_names": ["x", "y"], "arg_types": ["builtins.float", "builtins.float"], "bound_args": [], "def_extras": {"first_arg": null}, "fallback": "builtins.function", "implicit": false, "is_ellipsis_args": false, "name": "translation of Transform", "ret_type": {".class": "TupleType", "implicit": false, "items": ["builtins.float", "builtins.float", "builtins.float", "builtins.float", "builtins.float", "builtins.float"], "partial_fallback": "pymunk.transform.Transform"}, "variables": []}}, "is_overload": false, "var": {".class": "Var", "flags": ["is_initialized_in_class", "is_staticmethod", "is_ready"], "fullname": null, "name": "translation", "type": {".class": "CallableType", "arg_kinds": [0, 0], "arg_names": ["x", "y"], "arg_types": ["builtins.float", "builtins.float"], "bound_args": [], "def_extras": {"first_arg": null}, "fallback": "builtins.function", "implicit": false, "is_ellipsis_args": false, "name": "translation of Transform", "ret_type": {".class": "TupleType", "implicit": false, "items": ["builtins.float", "builtins.float", "builtins.float", "builtins.float", "builtins.float", "builtins.float"], "partial_fallback": "pymunk.transform.Transform"}, "variables": []}}}}, "tx": {".class": "SymbolTableNode", "kind": "Mdef", "node": {".class": "Var", "flags": ["is_property", "is_ready"], "fullname": "pymunk.transform.Transform.tx", "name": "tx", "type": "builtins.float"}}, "tx-redefinition": {".class": "SymbolTableNode", "cross_ref": "pymunk.transform.Transform.tx", "kind": "Mdef"}, "ty": {".class": "SymbolTableNode", "kind": "Mdef", "node": {".class": "Var", "flags": ["is_property", "is_ready"], "fullname": "pymunk.transform.Transform.ty", "name": "ty", "type": "builtins.float"}}, "ty-redefinition": {".class": "SymbolTableNode", "cross_ref": "pymunk.transform.Transform.ty", "kind": "Mdef"}}, "tuple_type": {".class": "TupleType", "implicit": false, "items": ["builtins.float", "builtins.float", "builtins.float", "builtins.float", "builtins.float", "builtins.float"], "partial_fallback": {".class": "Instance", "args": ["builtins.float"], "type_ref": "builtins.tuple"}}, "type_vars": [], "typeddict_type": null}}, "__doc__": {".class": "SymbolTableNode", "kind": "Gdef", "node": {".class": "Var", "flags": ["is_ready"], "fullname": "pymunk.transform.__doc__", "name": "__doc__", "type": "builtins.str"}}, "__file__": {".class": "SymbolTableNode", "kind": "Gdef", "node": {".class": "Var", "flags": ["is_ready"], "fullname": "pymunk.transform.__file__", "name": "__file__", "type": "builtins.str"}}, "__name__": {".class": "SymbolTableNode", "kind": "Gdef", "node": {".class": "Var", "flags": ["is_ready"], "fullname": "pymunk.transform.__name__", "name": "__name__", "type": "builtins.str"}}, "__package__": {".class": "SymbolTableNode", "kind": "Gdef", "node": {".class": "Var", "flags": ["is_ready"], "fullname": "pymunk.transform.__package__", "name": "__package__", "type": "builtins.str"}}, "math": {".class": "SymbolTableNode", "cross_ref": "math", "kind": "Gdef"}}, "path": "/home/michael/anaconda3/envs/simple-playgrounds/lib/python3.7/site-packages/pymunk/transform.py"}